deep_ast/__init__.py
deep_ast/_mixin.py
deep_ast-0.0.1.dist-info/entry_points.txt
deep_ast-0.0.1.dist-info/WHEEL
deep_ast-0.0.1.dist-info/METADATA
deep_ast-0.0.1.dist-info/RECORD
