Metadata-Version: 2.1
Name: deep-ast
Version: 0.0.1
Summary: Walks the entire AST tree, including calls to other functions.
Home-page: https://github.com/DontShaveTheYak/deep-ast
License: GPL-3.0-only
Keywords: ast,AST,testing,compile,parsing,conversion
Author: Levi Blaney
Author-email: shadycuz@gmail.com
Requires-Python: >=3.7,<4.0
Classifier: License :: OSI Approved :: GNU General Public License v3 (GPLv3)
Classifier: Programming Language :: Python :: 3
Classifier: Programming Language :: Python :: 3.7
Classifier: Programming Language :: Python :: 3.8
Classifier: Programming Language :: Python :: 3.9
Classifier: Programming Language :: Python :: 3.10
Requires-Dist: click (>=8.1.2,<9.0.0)
Requires-Dist: click-log (>=0.4.0,<0.5.0)
Project-URL: Repository, https://github.com/DontShaveTheYak/deep-ast
